reinforcement_learning_keras/__init__.py
reinforcement_learning_keras/agents/__init__.py
reinforcement_learning_keras/agents/agent_base.py
reinforcement_learning_keras/agents/components/__init__.py
reinforcement_learning_keras/agents/components/helpers/__init__.py
reinforcement_learning_keras/agents/components/helpers/env_builder.py
reinforcement_learning_keras/agents/components/helpers/tqdm_handler.py
reinforcement_learning_keras/agents/components/helpers/virtual_gpu.py
reinforcement_learning_keras/agents/components/history/__init__.py
reinforcement_learning_keras/agents/components/history/episode_report.py
reinforcement_learning_keras/agents/components/history/training_history.py
reinforcement_learning_keras/agents/components/replay_buffers/__init__.py
reinforcement_learning_keras/agents/components/replay_buffers/continuous_buffer.py
reinforcement_learning_keras/agents/components/replay_buffers/episodic_buffer.py
reinforcement_learning_keras/agents/components/replay_buffers/replay_buffer_base.py
reinforcement_learning_keras/agents/models/__init__.py
reinforcement_learning_keras/agents/models/conv_nn.py
reinforcement_learning_keras/agents/models/dense_nn.py
reinforcement_learning_keras/agents/models/dueling_conv_nn.py
reinforcement_learning_keras/agents/policy_gradient/__init__.py
reinforcement_learning_keras/agents/policy_gradient/loss.py
reinforcement_learning_keras/agents/policy_gradient/reinforce_agent.py
reinforcement_learning_keras/agents/q_learning/__init__.py
reinforcement_learning_keras/agents/q_learning/deep_q_agent.py
reinforcement_learning_keras/agents/q_learning/linear_q_agent.py
reinforcement_learning_keras/agents/q_learning/exploration/__init__.py
reinforcement_learning_keras/agents/q_learning/exploration/epsilon_greedy.py
reinforcement_learning_keras/agents/random/__init__.py
reinforcement_learning_keras/agents/random/random_agent.py
reinforcement_learning_keras/agents/random/random_model.py
reinforcement_learning_keras/enviroments/__init__.py
reinforcement_learning_keras-0.6.1.dist-info/LICENSE
reinforcement_learning_keras-0.6.1.dist-info/METADATA
reinforcement_learning_keras-0.6.1.dist-info/WHEEL
reinforcement_learning_keras-0.6.1.dist-info/top_level.txt
reinforcement_learning_keras-0.6.1.dist-info/RECORD
