Metadata-Version: 2.1
Name: reinforcement-learning-keras
Version: 0.6.1
Summary: UNKNOWN
Home-page: https://github.com/garethjns/reinforcement-learning-keras
Author: Gareth Jones
Author-email: garethgithub@gmail.com
License: UNKNOWN
Platform: UNKNOWN
Classifier: Programming Language :: Python :: 3
Classifier: Operating System :: OS Independent
Requires-Python: >=3.6
Requires-Dist: tensorflow (==2.3.1)
Requires-Dist: scikit-learn (==0.23.0)
Requires-Dist: matplotlib
Requires-Dist: gym[atari] (==0.17.1)
Requires-Dist: dataclasses
Requires-Dist: tqdm
Requires-Dist: seaborn
Requires-Dist: joblib
Requires-Dist: numpy
Requires-Dist: coverage
Requires-Dist: mock
Requires-Dist: opencv-python
